{
  "metadata": {
    "soundFile": "C:\\Users\\praty\\OneDrive\\Desktop\\ai-interviewer\\backend\\public\\audio\\speech_503_1773123170967.wav",
    "duration": 36.89
  },
  "mouthCues": [
    { "start": 0.00, "end": 0.15, "value": "X" },
    { "start": 0.15, "end": 0.39, "value": "B" },
    { "start": 0.39, "end": 0.53, "value": "D" },
    { "start": 0.53, "end": 0.60, "value": "C" },
    { "start": 0.60, "end": 0.68, "value": "A" },
    { "start": 0.68, "end": 0.91, "value": "C" },
    { "start": 0.91, "end": 1.12, "value": "B" },
    { "start": 1.12, "end": 1.14, "value": "A" },
    { "start": 1.14, "end": 1.21, "value": "C" },
    { "start": 1.21, "end": 1.28, "value": "A" },
    { "start": 1.28, "end": 1.64, "value": "B" },
    { "start": 1.64, "end": 1.73, "value": "A" },
    { "start": 1.73, "end": 1.84, "value": "G" },
    { "start": 1.84, "end": 1.91, "value": "E" },
    { "start": 1.91, "end": 2.19, "value": "C" },
    { "start": 2.19, "end": 2.40, "value": "B" },
    { "start": 2.40, "end": 2.48, "value": "A" },
    { "start": 2.48, "end": 2.59, "value": "C" },
    { "start": 2.59, "end": 2.80, "value": "B" },
    { "start": 2.80, "end": 2.87, "value": "C" },
    { "start": 2.87, "end": 3.01, "value": "D" },
    { "start": 3.01, "end": 3.08, "value": "C" },
    { "start": 3.08, "end": 3.17, "value": "A" },
    { "start": 3.17, "end": 3.23, "value": "E" },
    { "start": 3.23, "end": 3.35, "value": "B" },
    { "start": 3.35, "end": 3.42, "value": "F" },
    { "start": 3.42, "end": 3.49, "value": "C" },
    { "start": 3.49, "end": 3.63, "value": "B" },
    { "start": 3.63, "end": 3.77, "value": "C" },
    { "start": 3.77, "end": 4.19, "value": "B" },
    { "start": 4.19, "end": 4.26, "value": "E" },
    { "start": 4.26, "end": 4.33, "value": "F" },
    { "start": 4.33, "end": 4.40, "value": "B" },
    { "start": 4.40, "end": 4.51, "value": "A" },
    { "start": 4.51, "end": 4.57, "value": "B" },
    { "start": 4.57, "end": 4.70, "value": "D" },
    { "start": 4.70, "end": 5.05, "value": "B" },
    { "start": 5.05, "end": 5.13, "value": "A" },
    { "start": 5.13, "end": 5.19, "value": "C" },
    { "start": 5.19, "end": 5.59, "value": "B" },
    { "start": 5.59, "end": 5.88, "value": "X" },
    { "start": 5.88, "end": 5.93, "value": "B" },
    { "start": 5.93, "end": 5.98, "value": "C" },
    { "start": 5.98, "end": 6.26, "value": "B" },
    { "start": 6.26, "end": 6.45, "value": "F" },
    { "start": 6.45, "end": 6.50, "value": "E" },
    { "start": 6.50, "end": 6.82, "value": "C" },
    { "start": 6.82, "end": 6.96, "value": "B" },
    { "start": 6.96, "end": 7.10, "value": "G" },
    { "start": 7.10, "end": 7.17, "value": "D" },
    { "start": 7.17, "end": 7.59, "value": "B" },
    { "start": 7.59, "end": 7.66, "value": "F" },
    { "start": 7.66, "end": 7.73, "value": "C" },
    { "start": 7.73, "end": 7.80, "value": "B" },
    { "start": 7.80, "end": 7.88, "value": "A" },
    { "start": 7.88, "end": 7.94, "value": "C" },
    { "start": 7.94, "end": 8.27, "value": "B" },
    { "start": 8.27, "end": 9.16, "value": "X" },
    { "start": 9.16, "end": 9.34, "value": "B" },
    { "start": 9.34, "end": 9.44, "value": "D" },
    { "start": 9.44, "end": 9.48, "value": "C" },
    { "start": 9.48, "end": 9.61, "value": "A" },
    { "start": 9.61, "end": 9.75, "value": "B" },
    { "start": 9.75, "end": 9.82, "value": "C" },
    { "start": 9.82, "end": 10.03, "value": "B" },
    { "start": 10.03, "end": 10.10, "value": "G" },
    { "start": 10.10, "end": 10.17, "value": "B" },
    { "start": 10.17, "end": 10.25, "value": "A" },
    { "start": 10.25, "end": 10.30, "value": "C" },
    { "start": 10.30, "end": 10.48, "value": "B" },
    { "start": 10.48, "end": 10.56, "value": "A" },
    { "start": 10.56, "end": 10.81, "value": "C" },
    { "start": 10.81, "end": 10.90, "value": "A" },
    { "start": 10.90, "end": 11.30, "value": "B" },
    { "start": 11.30, "end": 11.43, "value": "C" },
    { "start": 11.43, "end": 11.50, "value": "H" },
    { "start": 11.50, "end": 11.71, "value": "B" },
    { "start": 11.71, "end": 12.06, "value": "C" },
    { "start": 12.06, "end": 12.40, "value": "B" },
    { "start": 12.40, "end": 12.44, "value": "G" },
    { "start": 12.44, "end": 12.51, "value": "E" },
    { "start": 12.51, "end": 12.59, "value": "A" },
    { "start": 12.59, "end": 12.79, "value": "C" },
    { "start": 12.79, "end": 12.86, "value": "B" },
    { "start": 12.86, "end": 13.00, "value": "E" },
    { "start": 13.00, "end": 13.21, "value": "B" },
    { "start": 13.21, "end": 13.28, "value": "G" },
    { "start": 13.28, "end": 13.56, "value": "B" },
    { "start": 13.56, "end": 14.40, "value": "X" },
    { "start": 14.40, "end": 14.57, "value": "B" },
    { "start": 14.57, "end": 14.67, "value": "D" },
    { "start": 14.67, "end": 14.71, "value": "C" },
    { "start": 14.71, "end": 14.83, "value": "A" },
    { "start": 14.83, "end": 14.93, "value": "B" },
    { "start": 14.93, "end": 15.00, "value": "C" },
    { "start": 15.00, "end": 15.28, "value": "B" },
    { "start": 15.28, "end": 15.35, "value": "G" },
    { "start": 15.35, "end": 15.42, "value": "B" },
    { "start": 15.42, "end": 15.50, "value": "A" },
    { "start": 15.50, "end": 15.57, "value": "C" },
    { "start": 15.57, "end": 16.34, "value": "B" },
    { "start": 16.34, "end": 16.41, "value": "E" },
    { "start": 16.41, "end": 16.83, "value": "B" },
    { "start": 16.83, "end": 16.96, "value": "C" },
    { "start": 16.96, "end": 17.17, "value": "B" },
    { "start": 17.17, "end": 17.52, "value": "C" },
    { "start": 17.52, "end": 17.83, "value": "B" },
    { "start": 17.83, "end": 17.94, "value": "G" },
    { "start": 17.94, "end": 18.01, "value": "E" },
    { "start": 18.01, "end": 18.15, "value": "C" },
    { "start": 18.15, "end": 18.22, "value": "B" },
    { "start": 18.22, "end": 18.29, "value": "C" },
    { "start": 18.29, "end": 18.40, "value": "A" },
    { "start": 18.40, "end": 18.73, "value": "B" },
    { "start": 18.73, "end": 18.87, "value": "C" },
    { "start": 18.87, "end": 19.01, "value": "B" },
    { "start": 19.01, "end": 19.15, "value": "G" },
    { "start": 19.15, "end": 20.03, "value": "X" },
    { "start": 20.03, "end": 20.14, "value": "B" },
    { "start": 20.14, "end": 20.21, "value": "F" },
    { "start": 20.21, "end": 20.28, "value": "B" },
    { "start": 20.28, "end": 20.36, "value": "A" },
    { "start": 20.36, "end": 20.46, "value": "C" },
    { "start": 20.46, "end": 20.53, "value": "B" },
    { "start": 20.53, "end": 20.60, "value": "E" },
    { "start": 20.60, "end": 21.02, "value": "B" },
    { "start": 21.02, "end": 21.09, "value": "C" },
    { "start": 21.09, "end": 21.44, "value": "B" },
    { "start": 21.44, "end": 21.58, "value": "C" },
    { "start": 21.58, "end": 21.65, "value": "E" },
    { "start": 21.65, "end": 22.01, "value": "B" },
    { "start": 22.01, "end": 22.07, "value": "C" },
    { "start": 22.07, "end": 22.14, "value": "H" },
    { "start": 22.14, "end": 22.21, "value": "C" },
    { "start": 22.21, "end": 22.28, "value": "B" },
    { "start": 22.28, "end": 22.63, "value": "F" },
    { "start": 22.63, "end": 22.77, "value": "B" },
    { "start": 22.77, "end": 22.84, "value": "G" },
    { "start": 22.84, "end": 22.91, "value": "C" },
    { "start": 22.91, "end": 23.12, "value": "B" },
    { "start": 23.12, "end": 23.20, "value": "A" },
    { "start": 23.20, "end": 23.39, "value": "D" },
    { "start": 23.39, "end": 23.46, "value": "H" },
    { "start": 23.46, "end": 23.88, "value": "B" },
    { "start": 23.88, "end": 24.72, "value": "X" },
    { "start": 24.72, "end": 24.99, "value": "C" },
    { "start": 24.99, "end": 25.06, "value": "B" },
    { "start": 25.06, "end": 25.34, "value": "C" },
    { "start": 25.34, "end": 25.41, "value": "B" },
    { "start": 25.41, "end": 25.49, "value": "A" },
    { "start": 25.49, "end": 25.88, "value": "B" },
    { "start": 25.88, "end": 26.30, "value": "C" },
    { "start": 26.30, "end": 26.37, "value": "B" },
    { "start": 26.37, "end": 26.44, "value": "C" },
    { "start": 26.44, "end": 26.72, "value": "B" },
    { "start": 26.72, "end": 26.86, "value": "C" },
    { "start": 26.86, "end": 26.93, "value": "B" },
    { "start": 26.93, "end": 27.07, "value": "C" },
    { "start": 27.07, "end": 27.14, "value": "E" },
    { "start": 27.14, "end": 27.35, "value": "F" },
    { "start": 27.35, "end": 27.42, "value": "B" },
    { "start": 27.42, "end": 28.26, "value": "X" },
    { "start": 28.26, "end": 28.41, "value": "B" },
    { "start": 28.41, "end": 28.48, "value": "C" },
    { "start": 28.48, "end": 28.55, "value": "B" },
    { "start": 28.55, "end": 28.83, "value": "C" },
    { "start": 28.83, "end": 28.90, "value": "B" },
    { "start": 28.90, "end": 28.97, "value": "H" },
    { "start": 28.97, "end": 29.04, "value": "C" },
    { "start": 29.04, "end": 29.32, "value": "B" },
    { "start": 29.32, "end": 29.39, "value": "C" },
    { "start": 29.39, "end": 29.67, "value": "B" },
    { "start": 29.67, "end": 29.74, "value": "C" },
    { "start": 29.74, "end": 29.81, "value": "G" },
    { "start": 29.81, "end": 30.02, "value": "B" },
    { "start": 30.02, "end": 30.10, "value": "A" },
    { "start": 30.10, "end": 30.15, "value": "G" },
    { "start": 30.15, "end": 30.20, "value": "B" },
    { "start": 30.20, "end": 30.28, "value": "A" },
    { "start": 30.28, "end": 30.37, "value": "C" },
    { "start": 30.37, "end": 30.44, "value": "B" },
    { "start": 30.44, "end": 30.51, "value": "C" },
    { "start": 30.51, "end": 30.93, "value": "B" },
    { "start": 30.93, "end": 31.23, "value": "X" },
    { "start": 31.23, "end": 31.31, "value": "B" },
    { "start": 31.31, "end": 31.52, "value": "H" },
    { "start": 31.52, "end": 31.73, "value": "B" },
    { "start": 31.73, "end": 31.87, "value": "C" },
    { "start": 31.87, "end": 31.94, "value": "B" },
    { "start": 31.94, "end": 32.01, "value": "C" },
    { "start": 32.01, "end": 32.15, "value": "B" },
    { "start": 32.15, "end": 32.22, "value": "C" },
    { "start": 32.22, "end": 32.33, "value": "A" },
    { "start": 32.33, "end": 32.39, "value": "B" },
    { "start": 32.39, "end": 32.52, "value": "E" },
    { "start": 32.52, "end": 32.66, "value": "B" },
    { "start": 32.66, "end": 32.94, "value": "C" },
    { "start": 32.94, "end": 33.09, "value": "A" },
    { "start": 33.09, "end": 33.35, "value": "B" },
    { "start": 33.35, "end": 33.44, "value": "A" },
    { "start": 33.44, "end": 33.52, "value": "B" },
    { "start": 33.52, "end": 33.94, "value": "F" },
    { "start": 33.94, "end": 34.08, "value": "B" },
    { "start": 34.08, "end": 36.89, "value": "X" }
  ]
}
