{
  "metadata": {
    "soundFile": "C:\\Users\\praty\\OneDrive\\Desktop\\ai-interviewer\\backend\\public\\audio\\speech_2_1775244231926.wav",
    "duration": 9.12
  },
  "mouthCues": [
    { "start": 0.00, "end": 0.19, "value": "X" },
    { "start": 0.19, "end": 0.30, "value": "B" },
    { "start": 0.30, "end": 0.58, "value": "C" },
    { "start": 0.58, "end": 0.79, "value": "B" },
    { "start": 0.79, "end": 0.87, "value": "A" },
    { "start": 0.87, "end": 1.04, "value": "B" },
    { "start": 1.04, "end": 1.25, "value": "F" },
    { "start": 1.25, "end": 1.32, "value": "B" },
    { "start": 1.32, "end": 1.50, "value": "X" },
    { "start": 1.50, "end": 1.54, "value": "B" },
    { "start": 1.54, "end": 1.58, "value": "C" },
    { "start": 1.58, "end": 1.65, "value": "B" },
    { "start": 1.65, "end": 1.72, "value": "H" },
    { "start": 1.72, "end": 1.86, "value": "C" },
    { "start": 1.86, "end": 1.93, "value": "G" },
    { "start": 1.93, "end": 2.07, "value": "E" },
    { "start": 2.07, "end": 2.14, "value": "B" },
    { "start": 2.14, "end": 2.42, "value": "E" },
    { "start": 2.42, "end": 2.50, "value": "A" },
    { "start": 2.50, "end": 2.57, "value": "C" },
    { "start": 2.57, "end": 2.64, "value": "B" },
    { "start": 2.64, "end": 2.72, "value": "A" },
    { "start": 2.72, "end": 3.19, "value": "B" },
    { "start": 3.19, "end": 3.33, "value": "E" },
    { "start": 3.33, "end": 3.68, "value": "B" },
    { "start": 3.68, "end": 3.95, "value": "X" },
    { "start": 3.95, "end": 4.20, "value": "B" },
    { "start": 4.20, "end": 4.34, "value": "C" },
    { "start": 4.34, "end": 4.41, "value": "E" },
    { "start": 4.41, "end": 4.49, "value": "A" },
    { "start": 4.49, "end": 4.53, "value": "B" },
    { "start": 4.53, "end": 4.61, "value": "A" },
    { "start": 4.61, "end": 4.78, "value": "C" },
    { "start": 4.78, "end": 4.86, "value": "A" },
    { "start": 4.86, "end": 5.03, "value": "C" },
    { "start": 5.03, "end": 5.10, "value": "F" },
    { "start": 5.10, "end": 5.17, "value": "B" },
    { "start": 5.17, "end": 5.25, "value": "A" },
    { "start": 5.25, "end": 5.59, "value": "B" },
    { "start": 5.59, "end": 5.66, "value": "G" },
    { "start": 5.66, "end": 5.94, "value": "F" },
    { "start": 5.94, "end": 6.01, "value": "B" },
    { "start": 6.01, "end": 6.15, "value": "C" },
    { "start": 6.15, "end": 6.29, "value": "B" },
    { "start": 6.29, "end": 9.12, "value": "X" }
  ]
}
