{
  "metadata": {
    "soundFile": "C:\\Users\\praty\\OneDrive\\Desktop\\ai-interviewer\\backend\\public\\audio\\speech_378_1772914625992.wav",
    "duration": 7.37
  },
  "mouthCues": [
    { "start": 0.00, "end": 0.16, "value": "X" },
    { "start": 0.16, "end": 0.22, "value": "B" },
    { "start": 0.22, "end": 0.27, "value": "C" },
    { "start": 0.27, "end": 0.48, "value": "B" },
    { "start": 0.48, "end": 0.62, "value": "D" },
    { "start": 0.62, "end": 0.69, "value": "B" },
    { "start": 0.69, "end": 0.83, "value": "H" },
    { "start": 0.83, "end": 0.90, "value": "C" },
    { "start": 0.90, "end": 0.97, "value": "B" },
    { "start": 0.97, "end": 1.05, "value": "A" },
    { "start": 1.05, "end": 1.16, "value": "B" },
    { "start": 1.16, "end": 1.23, "value": "C" },
    { "start": 1.23, "end": 1.44, "value": "B" },
    { "start": 1.44, "end": 1.58, "value": "X" },
    { "start": 1.58, "end": 1.64, "value": "B" },
    { "start": 1.64, "end": 1.91, "value": "C" },
    { "start": 1.91, "end": 1.98, "value": "F" },
    { "start": 1.98, "end": 2.12, "value": "E" },
    { "start": 2.12, "end": 2.55, "value": "B" },
    { "start": 2.55, "end": 2.59, "value": "H" },
    { "start": 2.59, "end": 2.66, "value": "C" },
    { "start": 2.66, "end": 3.01, "value": "B" },
    { "start": 3.01, "end": 3.08, "value": "G" },
    { "start": 3.08, "end": 3.15, "value": "F" },
    { "start": 3.15, "end": 3.43, "value": "B" },
    { "start": 3.43, "end": 3.50, "value": "C" },
    { "start": 3.50, "end": 3.71, "value": "F" },
    { "start": 3.71, "end": 3.78, "value": "B" },
    { "start": 3.78, "end": 3.85, "value": "C" },
    { "start": 3.85, "end": 4.06, "value": "B" },
    { "start": 4.06, "end": 4.27, "value": "C" },
    { "start": 4.27, "end": 4.34, "value": "B" },
    { "start": 4.34, "end": 4.55, "value": "E" },
    { "start": 4.55, "end": 7.37, "value": "X" }
  ]
}
