{
  "metadata": {
    "soundFile": "C:\\Users\\praty\\OneDrive\\Desktop\\ai-interviewer\\backend\\public\\audio\\speech_545_1773738131106.wav",
    "duration": 11.31
  },
  "mouthCues": [
    { "start": 0.00, "end": 0.17, "value": "X" },
    { "start": 0.17, "end": 0.23, "value": "B" },
    { "start": 0.23, "end": 0.29, "value": "F" },
    { "start": 0.29, "end": 0.36, "value": "C" },
    { "start": 0.36, "end": 0.64, "value": "B" },
    { "start": 0.64, "end": 0.72, "value": "A" },
    { "start": 0.72, "end": 0.78, "value": "C" },
    { "start": 0.78, "end": 1.11, "value": "B" },
    { "start": 1.11, "end": 1.18, "value": "G" },
    { "start": 1.18, "end": 1.32, "value": "C" },
    { "start": 1.32, "end": 1.39, "value": "B" },
    { "start": 1.39, "end": 1.46, "value": "C" },
    { "start": 1.46, "end": 1.67, "value": "B" },
    { "start": 1.67, "end": 1.74, "value": "C" },
    { "start": 1.74, "end": 1.95, "value": "B" },
    { "start": 1.95, "end": 2.02, "value": "C" },
    { "start": 2.02, "end": 2.37, "value": "B" },
    { "start": 2.37, "end": 2.58, "value": "C" },
    { "start": 2.58, "end": 2.79, "value": "B" },
    { "start": 2.79, "end": 2.86, "value": "C" },
    { "start": 2.86, "end": 2.93, "value": "B" },
    { "start": 2.93, "end": 3.01, "value": "A" },
    { "start": 3.01, "end": 3.14, "value": "C" },
    { "start": 3.14, "end": 3.28, "value": "B" },
    { "start": 3.28, "end": 3.42, "value": "C" },
    { "start": 3.42, "end": 3.78, "value": "B" },
    { "start": 3.78, "end": 4.13, "value": "C" },
    { "start": 4.13, "end": 4.20, "value": "E" },
    { "start": 4.20, "end": 4.48, "value": "B" },
    { "start": 4.48, "end": 4.62, "value": "G" },
    { "start": 4.62, "end": 4.69, "value": "E" },
    { "start": 4.69, "end": 4.83, "value": "C" },
    { "start": 4.83, "end": 5.32, "value": "B" },
    { "start": 5.32, "end": 5.60, "value": "C" },
    { "start": 5.60, "end": 5.88, "value": "B" },
    { "start": 5.88, "end": 5.95, "value": "F" },
    { "start": 5.95, "end": 6.16, "value": "E" },
    { "start": 6.16, "end": 6.30, "value": "B" },
    { "start": 6.30, "end": 6.37, "value": "C" },
    { "start": 6.37, "end": 6.65, "value": "B" },
    { "start": 6.65, "end": 6.72, "value": "E" },
    { "start": 6.72, "end": 6.79, "value": "G" },
    { "start": 6.79, "end": 6.93, "value": "B" },
    { "start": 6.93, "end": 7.18, "value": "D" },
    { "start": 7.18, "end": 7.25, "value": "E" },
    { "start": 7.25, "end": 7.49, "value": "F" },
    { "start": 7.49, "end": 7.56, "value": "E" },
    { "start": 7.56, "end": 7.64, "value": "A" },
    { "start": 7.64, "end": 7.82, "value": "E" },
    { "start": 7.82, "end": 8.10, "value": "B" },
    { "start": 8.10, "end": 8.17, "value": "C" },
    { "start": 8.17, "end": 8.24, "value": "E" },
    { "start": 8.24, "end": 8.31, "value": "B" },
    { "start": 8.31, "end": 8.44, "value": "A" },
    { "start": 8.44, "end": 8.52, "value": "B" },
    { "start": 8.52, "end": 11.31, "value": "X" }
  ]
}
