{
  "metadata": {
    "soundFile": "C:\\Users\\praty\\OneDrive\\Desktop\\ai-interviewer\\backend\\public\\audio\\speech_428_1773005584042.wav",
    "duration": 8.43
  },
  "mouthCues": [
    { "start": 0.00, "end": 0.16, "value": "X" },
    { "start": 0.16, "end": 0.20, "value": "B" },
    { "start": 0.20, "end": 0.31, "value": "H" },
    { "start": 0.31, "end": 0.38, "value": "C" },
    { "start": 0.38, "end": 0.52, "value": "F" },
    { "start": 0.52, "end": 0.80, "value": "B" },
    { "start": 0.80, "end": 0.93, "value": "A" },
    { "start": 0.93, "end": 0.98, "value": "B" },
    { "start": 0.98, "end": 1.09, "value": "C" },
    { "start": 1.09, "end": 1.16, "value": "B" },
    { "start": 1.16, "end": 1.24, "value": "A" },
    { "start": 1.24, "end": 1.42, "value": "B" },
    { "start": 1.42, "end": 1.50, "value": "A" },
    { "start": 1.50, "end": 1.59, "value": "C" },
    { "start": 1.59, "end": 1.87, "value": "B" },
    { "start": 1.87, "end": 1.94, "value": "G" },
    { "start": 1.94, "end": 2.01, "value": "B" },
    { "start": 2.01, "end": 2.08, "value": "C" },
    { "start": 2.08, "end": 2.15, "value": "B" },
    { "start": 2.15, "end": 2.23, "value": "A" },
    { "start": 2.23, "end": 2.41, "value": "E" },
    { "start": 2.41, "end": 2.48, "value": "C" },
    { "start": 2.48, "end": 2.55, "value": "B" },
    { "start": 2.55, "end": 2.62, "value": "C" },
    { "start": 2.62, "end": 2.70, "value": "A" },
    { "start": 2.70, "end": 2.95, "value": "B" },
    { "start": 2.95, "end": 3.23, "value": "C" },
    { "start": 3.23, "end": 3.30, "value": "E" },
    { "start": 3.30, "end": 3.58, "value": "F" },
    { "start": 3.58, "end": 3.79, "value": "B" },
    { "start": 3.79, "end": 3.87, "value": "A" },
    { "start": 3.87, "end": 4.11, "value": "C" },
    { "start": 4.11, "end": 4.25, "value": "B" },
    { "start": 4.25, "end": 4.39, "value": "C" },
    { "start": 4.39, "end": 4.46, "value": "G" },
    { "start": 4.46, "end": 4.53, "value": "B" },
    { "start": 4.53, "end": 4.60, "value": "E" },
    { "start": 4.60, "end": 4.67, "value": "F" },
    { "start": 4.67, "end": 4.81, "value": "E" },
    { "start": 4.81, "end": 5.02, "value": "B" },
    { "start": 5.02, "end": 5.16, "value": "C" },
    { "start": 5.16, "end": 5.30, "value": "B" },
    { "start": 5.30, "end": 5.37, "value": "C" },
    { "start": 5.37, "end": 5.44, "value": "E" },
    { "start": 5.44, "end": 5.51, "value": "F" },
    { "start": 5.51, "end": 5.61, "value": "A" },
    { "start": 5.61, "end": 8.43, "value": "X" }
  ]
}
